dataclass_mapper/__init__.py
dataclass_mapper/assignments/__init__.py
dataclass_mapper/assignments/assignment.py
dataclass_mapper/assignments/dict.py
dataclass_mapper/assignments/function.py
dataclass_mapper/assignments/list.py
dataclass_mapper/assignments/recursive.py
dataclass_mapper/assignments/simple.py
dataclass_mapper/assignments/utils.py
dataclass_mapper/classmeta.py
dataclass_mapper/code_generator.py
dataclass_mapper/enum.py
dataclass_mapper/implementations/__init__.py
dataclass_mapper/implementations/base.py
dataclass_mapper/implementations/dataclasses.py
dataclass_mapper/implementations/pydantic_v1.py
dataclass_mapper/implementations/pydantic_v2.py
dataclass_mapper/implementations/utils.py
dataclass_mapper/mapper.py
dataclass_mapper/mapping_method.py
dataclass_mapper/namespace.py
dataclass_mapper/py.typed
dataclass_mapper/utils.py
dataclass_mapper-1.9.3.dist-info/LICENSE.md
dataclass_mapper-1.9.3.dist-info/WHEEL
dataclass_mapper-1.9.3.dist-info/METADATA
dataclass_mapper-1.9.3.dist-info/RECORD
