Metadata-Version: 2.1
Name: dataclass-mapper
Version: 1.9.3
Summary: Autogenerate mappings between dataclasses
Home-page: https://dataclass-mapper.readthedocs.io
License: MIT
Keywords: dataclass,pydantic,python,automation
Author: Jakob Kogler
Author-email: jakob.kogler@gmail.com
Requires-Python: >=3.8,<4.0
Classifier: Framework :: Pydantic
Classifier: Framework :: Pydantic :: 1
Classifier: Framework :: Pydantic :: 2
Classifier: License :: OSI Approved :: MIT License
Classifier: Programming Language :: Python :: 3
Classifier: Programming Language :: Python :: 3.8
Classifier: Programming Language :: Python :: 3.9
Classifier: Programming Language :: Python :: 3.10
Classifier: Programming Language :: Python :: 3.11
Classifier: Programming Language :: Python :: 3.10
Classifier: Programming Language :: Python :: 3.11
Classifier: Programming Language :: Python :: 3.12
Classifier: Programming Language :: Python :: 3.8
Classifier: Programming Language :: Python :: 3.9
Classifier: Topic :: Software Development :: Code Generators
Provides-Extra: pydantic
Requires-Dist: pydantic (>=1.9.0); extra == "pydantic"
Project-URL: Documentation, https://dataclass-mapper.readthedocs.io
Project-URL: Repository, https://github.com/dataclass-mapper/dataclass-mapper
